setup.py
odoo/addons/somconnexio_application/README.rst
odoo/addons/somconnexio_application/__init__.py
odoo/addons/somconnexio_application/__manifest__.py
odoo_addon_somconnexio_application.egg-info/PKG-INFO
odoo_addon_somconnexio_application.egg-info/SOURCES.txt
odoo_addon_somconnexio_application.egg-info/dependency_links.txt
odoo_addon_somconnexio_application.egg-info/not-zip-safe
odoo_addon_somconnexio_application.egg-info/requires.txt
odoo_addon_somconnexio_application.egg-info/top_level.txt