Metadata-Version: 2.4
Name: odoo-addon-somconnexio_application
Version: 16.0.1.0.0
Summary: Som Connexió's application with custom Odoo addons as dependencies that fulfill the cooperative requirements.
Home-page: https://coopdevs.org
Author: Som Connexió SCCL, Coopdevs Treball SCCL
License: AGPL-3
Classifier: Programming Language :: Python
Classifier: Framework :: Odoo
Classifier: Framework :: Odoo :: 16.0
Classifier: License :: OSI Approved :: GNU Affero General Public License v3
Requires-Python: >=3.10
Requires-Dist: odoo-addon-base_rest_somconnexio<16.1dev,>=16.0dev
Requires-Dist: odoo-addon-contract_api_somconnexio<16.1dev,>=16.0dev
Requires-Dist: odoo-addon-contract_group_somconnexio<16.1dev,>=16.0dev
Requires-Dist: odoo-addon-cooperator_api_somconnexio<16.1dev,>=16.0dev
Requires-Dist: odoo-addon-cooperator_somconnexio<16.1dev,>=16.0dev
Requires-Dist: odoo-addon-cooperator_sponsorship<16.1dev,>=16.0dev
Requires-Dist: odoo-addon-correos_somconnexio<16.1dev,>=16.0dev
Requires-Dist: odoo-addon-crm_lead_api_somconnexio<16.1dev,>=16.0dev
Requires-Dist: odoo-addon-delivery_somconnexio<16.1dev,>=16.0dev
Requires-Dist: odoo-addon-filmin_somconnexio<16.1dev,>=16.0dev
Requires-Dist: odoo-addon-hide_sequence_gaps_warning<16.1dev,>=16.0dev
Requires-Dist: odoo-addon-hr_assistance_somconnexio<16.1dev,>=16.0dev
Requires-Dist: odoo-addon-invoice_somconnexio<16.1dev,>=16.0dev
Requires-Dist: odoo-addon-marginalized_groups_somconnexio<16.1dev,>=16.0dev
Requires-Dist: odoo-addon-mass_mailing_somconnexio<16.1dev,>=16.0dev
Requires-Dist: odoo-addon-multimedia_api_somconnexio<16.1dev,>=16.0dev
Requires-Dist: odoo-addon-multimedia_somconnexio<16.1dev,>=16.0dev
Requires-Dist: odoo-addon-oficinavirtual_somconnexio<16.1dev,>=16.0dev
Requires-Dist: odoo-addon-opencell_somconnexio<16.1dev,>=16.0dev
Requires-Dist: odoo-addon-otrs_somconnexio<16.1dev,>=16.0dev
Requires-Dist: odoo-addon-product_product_sale_subscription_template<16.1dev,>=16.0dev
Requires-Dist: odoo-addon-res_partner_api_somconnexio<16.1dev,>=16.0dev
Requires-Dist: odoo-addon-somconnexio<16.1dev,>=16.0dev
Requires-Dist: odoo-addon-switchboard_somconnexio<16.1dev,>=16.0dev
Requires-Dist: odoo<16.1dev,>=16.0a
Dynamic: author
Dynamic: classifier
Dynamic: description
Dynamic: home-page
Dynamic: license
Dynamic: requires-dist
Dynamic: requires-python
Dynamic: summary
